flask_json_validator/__init__.py
Flask_JIV-0.0.2.dist-info/LICENSE
Flask_JIV-0.0.2.dist-info/METADATA
Flask_JIV-0.0.2.dist-info/WHEEL
Flask_JIV-0.0.2.dist-info/top_level.txt
Flask_JIV-0.0.2.dist-info/RECORD
